<annotation>
	<folder>JPEGImages</folder>
	<filename>0089.jpg</filename>
	<source>
		<database>Unknown</database>
	</source>
	<size>
		<width>608</width>
		<height>608</height>
		<depth>3</depth>
	</size>
	<segmented>0</segmented>
	<object>
		<name>boerner</name>
		<pose>Unspecified</pose>
		<truncated>0</truncated>
		<difficult>0</difficult>
		<bndbox>
			<xmin>259</xmin>
			<ymin>367</ymin>
			<xmax>294</xmax>
			<ymax>433</ymax>
		</bndbox>
	</object>
	<object>
		<name>leconte</name>
		<pose>Unspecified</pose>
		<truncated>0</truncated>
		<difficult>0</difficult>
		<bndbox>
			<xmin>320</xmin>
			<ymin>329</ymin>
			<xmax>383</xmax>
			<ymax>365</ymax>
		</bndbox>
	</object>
	<object>
		<name>coleoptera</name>
		<pose>Unspecified</pose>
		<truncated>0</truncated>
		<difficult>0</difficult>
		<bndbox>
			<xmin>381</xmin>
			<ymin>297</ymin>
			<xmax>420</xmax>
			<ymax>332</ymax>
		</bndbox>
	</object>
	<object>
		<name>linnaeus</name>
		<pose>Unspecified</pose>
		<truncated>0</truncated>
		<difficult>0</difficult>
		<bndbox>
			<xmin>201</xmin>
			<ymin>260</ymin>
			<xmax>244</xmax>
			<ymax>285</ymax>
		</bndbox>
	</object>
	<object>
		<name>armandi</name>
		<pose>Unspecified</pose>
		<truncated>0</truncated>
		<difficult>0</difficult>
		<bndbox>
			<xmin>303</xmin>
			<ymin>250</ymin>
			<xmax>337</xmax>
			<ymax>296</ymax>
		</bndbox>
	</object>
</annotation>
