<annotation>
	<folder>JPEGImages</folder>
	<filename>0168.jpg</filename>
	<source>
		<database>Unknown</database>
	</source>
	<size>
		<width>707</width>
		<height>707</height>
		<depth>3</depth>
	</size>
	<segmented>0</segmented>
	<object>
		<name>boerner</name>
		<pose>Unspecified</pose>
		<truncated>0</truncated>
		<difficult>0</difficult>
		<bndbox>
			<xmin>381</xmin>
			<ymin>395</ymin>
			<xmax>418</xmax>
			<ymax>483</ymax>
		</bndbox>
	</object>
	<object>
		<name>leconte</name>
		<pose>Unspecified</pose>
		<truncated>0</truncated>
		<difficult>0</difficult>
		<bndbox>
			<xmin>229</xmin>
			<ymin>381</ymin>
			<xmax>307</xmax>
			<ymax>430</ymax>
		</bndbox>
	</object>
	<object>
		<name>coleoptera</name>
		<pose>Unspecified</pose>
		<truncated>0</truncated>
		<difficult>0</difficult>
		<bndbox>
			<xmin>324</xmin>
			<ymin>355</ymin>
			<xmax>367</xmax>
			<ymax>385</ymax>
		</bndbox>
	</object>
	<object>
		<name>armandi</name>
		<pose>Unspecified</pose>
		<truncated>0</truncated>
		<difficult>0</difficult>
		<bndbox>
			<xmin>397</xmin>
			<ymin>303</ymin>
			<xmax>441</xmax>
			<ymax>352</ymax>
		</bndbox>
	</object>
	<object>
		<name>linnaeus</name>
		<pose>Unspecified</pose>
		<truncated>0</truncated>
		<difficult>0</difficult>
		<bndbox>
			<xmin>300</xmin>
			<ymin>269</ymin>
			<xmax>330</xmax>
			<ymax>328</ymax>
		</bndbox>
	</object>
</annotation>
